pdf2jpg/__init__.py
pdf2jpg/pdf2jpg.jar
pdf2jpg/pdf2jpg.py
pdf2jpg-1.1.dist-info/METADATA
pdf2jpg-1.1.dist-info/WHEEL
pdf2jpg-1.1.dist-info/top_level.txt
pdf2jpg-1.1.dist-info/RECORD
